starcli/__init__.py
starcli/__main__.py
starcli/layouts.py
starcli/search.py
starcli-2.18.1.dist-info/LICENSE
starcli-2.18.1.dist-info/METADATA
starcli-2.18.1.dist-info/WHEEL
starcli-2.18.1.dist-info/entry_points.txt
starcli-2.18.1.dist-info/top_level.txt
starcli-2.18.1.dist-info/RECORD
