Metadata-Version: 2.1
Name: starcli
Version: 2.18.1
Summary: Browse popular projects on github by star trends from your command line
Home-page: https://github.com/hedyhli/starcli
Author: hedy
Author-email: hedy@tilde.cafe
License: MIT
Platform: UNKNOWN
Classifier: License :: OSI Approved :: MIT License
Classifier: Programming Language :: Python :: 3
Classifier: Programming Language :: Python :: 3.7
Classifier: Programming Language :: Python :: 3.8
Classifier: Programming Language :: Python :: 3.9
Classifier: Programming Language :: Python :: 3.10
Classifier: Programming Language :: Python :: 3.11
Requires-Python: >=3.6
Requires-Dist: Click <8.0,>=7.0
Requires-Dist: gtrending <1.0.0,>=0.3.0
Requires-Dist: requests <3.0.0,>=2.22.0
Requires-Dist: rich <14.0.0,>=4.0.0
Requires-Dist: xdg <6.0.0,>=5.1.1
